mlx_gen_parity/__init__.py
mlx_gen_parity/adapters.py
mlx_gen_parity/api.py
mlx_gen_parity/cli.py
mlx_gen_parity/diagnostics.py
mlx_gen_parity/injection.py
mlx_gen_parity/interop.py
mlx_gen_parity/loader.py
mlx_gen_parity/sampling.py
mlx_gen_parity/training.py
mlx_gen_parity/utils.py
mlx_gen_parity/data/loader.py
mlx_gen_parity/rl/ppo.py
mlx_gen_parity/rl/utils.py
mlx_gen_parity/tests/harness.py
mlx_gen_parity/tests/parity_hf.py
mlx_gen_parity/tests/parity_suite.py
mlx_gen_parity/tests/perf_bench.py
mlx_gen_parity/tests/utils_demo.py
mlx_gen_parity-0.1.5.dist-info/licenses/LICENSE
mlx_gen_parity-0.1.5.dist-info/METADATA
mlx_gen_parity-0.1.5.dist-info/WHEEL
mlx_gen_parity-0.1.5.dist-info/entry_points.txt
mlx_gen_parity-0.1.5.dist-info/top_level.txt
mlx_gen_parity-0.1.5.dist-info/RECORD
