Metadata-Version: 2.4
Name: mlx-gen-parity
Version: 0.1.5
Summary: MLX generation parity utils with HF/Torch-compatible sampling, processors, and steering hooks
Author: Your Team
Project-URL: Homepage, https://github.com/strangeloopcanon/mlx-genkit
Requires-Python: >=3.9
License-File: LICENSE
Requires-Dist: mlx>=0.17.0
Requires-Dist: mlx-lm>=0.17.0
Requires-Dist: transformers>=4.40.0; python_version >= "3.9"
Requires-Dist: mlx-genkit>=0.2.0
Dynamic: license-file
